gcp_resource_analysis/__init__.py
gcp_resource_analysis/client.py
gcp_resource_analysis/gcp_compute_governance.py
gcp_resource_analysis/gcp_container_analysis.py
gcp_resource_analysis/gcp_iam_analysis.py
gcp_resource_analysis/gcp_network_analysis.py
gcp_resource_analysis/gcp_storage_analysis.py
gcp_resource_analysis/utils.py
gcp_resource_analysis/models/__init__.py
gcp_resource_analysis/models/compute_governance.py
gcp_resource_analysis/models/container_analysis.py
gcp_resource_analysis/models/iam_analysis.py
gcp_resource_analysis/models/network_analysis.py
gcp_resource_analysis/models/storage_analysis.py
gcp_resource_analysis-1.0.11.dist-info/licenses/LICENSE
gcp_resource_analysis-1.0.11.dist-info/METADATA
gcp_resource_analysis-1.0.11.dist-info/WHEEL
gcp_resource_analysis-1.0.11.dist-info/top_level.txt
gcp_resource_analysis-1.0.11.dist-info/RECORD
