Metadata-Version: 2.4
Name: gcp-resource-analysis
Version: 1.0.11
Summary: Python client for GCP Resource Analysis with security, compliance & optimization insights
Home-page: https://github.com/hasura/gcp-resource-analysis
Author: GCP Resource Analysis
Author-email: GCP Resource Analysis <ken@promptql.io>
Maintainer-email: GCP Resource Analysis <ken@promptql.io>
License: MIT
Project-URL: Homepage, https://github.com/hasura/gcp-resource-analysis
Project-URL: Documentation, https://github.com/hasura/gcp-resource-analysis/blob/main/README.md
Project-URL: Repository, https://github.com/hasura/gcp-resource-analysis
Project-URL: Bug Tracker, https://github.com/hasura/gcp-resource-analysis/issues
Project-URL: Changelog, https://github.com/hasura/gcp-resource-analysis/blob/main/CHANGELOG.md
Keywords: gcp,google-cloud,resource-analysis,cloud-asset-inventory,security,compliance,optimization,governance,api-client,cost-optimization
Platform: any
Classifier: Development Status :: 4 - Beta
Classifier: Intended Audience :: Developers
Classifier: Intended Audience :: System Administrators
Classifier: License :: OSI Approved :: MIT License
Classifier: Operating System :: OS Independent
Classifier: Programming Language :: Python :: 3
Classifier: Programming Language :: Python :: 3.8
Classifier: Programming Language :: Python :: 3.9
Classifier: Programming Language :: Python :: 3.10
Classifier: Programming Language :: Python :: 3.11
Classifier: Programming Language :: Python :: 3.12
Classifier: Topic :: Software Development :: Libraries :: Python Modules
Classifier: Topic :: System :: Systems Administration
Classifier: Topic :: Security
Classifier: Topic :: Internet :: WWW/HTTP :: Dynamic Content
Requires-Python: >=3.8
License-File: LICENSE
Requires-Dist: requests<3.0.0,>=2.28.0
Requires-Dist: python-dotenv<2.0.0,>=0.19.0
Requires-Dist: pydantic>=2.11.7
Requires-Dist: google-auth<3.0.0,>=2.17.0
Requires-Dist: google-auth-oauthlib<2.0.0,>=1.0.0
Requires-Dist: google-auth-httplib2<1.0.0,>=0.1.0
Requires-Dist: google-cloud-asset<4.0.0,>=3.20.0
Requires-Dist: google-cloud-resource-manager<2.0.0,>=1.10.0
Provides-Extra: dev
Requires-Dist: pytest<8.0.0,>=7.0.0; extra == "dev"
Requires-Dist: pytest-cov<5.0.0,>=4.0.0; extra == "dev"
Requires-Dist: black<24.0.0,>=22.0.0; extra == "dev"
Requires-Dist: flake8<7.0.0,>=5.0.0; extra == "dev"
Requires-Dist: mypy<2.0.0,>=1.0.0; extra == "dev"
Provides-Extra: docs
Requires-Dist: sphinx<7.0.0,>=5.0.0; extra == "docs"
Requires-Dist: sphinx-rtd-theme<2.0.0,>=1.0.0; extra == "docs"
Provides-Extra: all
Requires-Dist: google-auth<3.0.0,>=2.17.0; extra == "all"
Requires-Dist: google-auth-oauthlib<2.0.0,>=1.0.0; extra == "all"
Requires-Dist: google-auth-httplib2<1.0.0,>=0.1.0; extra == "all"
Requires-Dist: google-cloud-asset<4.0.0,>=3.20.0; extra == "all"
Requires-Dist: google-cloud-resource-manager<2.0.0,>=1.10.0; extra == "all"
Requires-Dist: pytest<8.0.0,>=7.0.0; extra == "all"
Requires-Dist: pytest-cov<5.0.0,>=4.0.0; extra == "all"
Requires-Dist: black<24.0.0,>=22.0.0; extra == "all"
Requires-Dist: flake8<7.0.0,>=5.0.0; extra == "all"
Requires-Dist: mypy<2.0.0,>=1.0.0; extra == "all"
Requires-Dist: sphinx<7.0.0,>=5.0.0; extra == "all"
Requires-Dist: sphinx-rtd-theme<2.0.0,>=1.0.0; extra == "all"
Dynamic: author
Dynamic: home-page
Dynamic: license-file
Dynamic: platform
Dynamic: requires-python
